schrodinet/__init__.py
schrodinet/__version__.py
schrodinet/sampler/__init__.py
schrodinet/sampler/hamiltonian.py
schrodinet/sampler/metropolis.py
schrodinet/sampler/sampler_base.py
schrodinet/sampler/walkers.py
schrodinet/solver/__init__.py
schrodinet/solver/plot_data.py
schrodinet/solver/plot_potential.py
schrodinet/solver/solver_base.py
schrodinet/solver/solver_potential.py
schrodinet/solver/torch_utils.py
schrodinet/wavefunction/__init__.py
schrodinet/wavefunction/mesh_utils.py
schrodinet/wavefunction/rbf.py
schrodinet/wavefunction/wf_base.py
schrodinet/wavefunction/wf_potential.py
schrodinet/wavefunction/wf_potential_2d.py
tests/__init__.py
tests/test_ho1d.py
schrodinet-0.1.2.dist-info/LICENSE
schrodinet-0.1.2.dist-info/METADATA
schrodinet-0.1.2.dist-info/NOTICE
schrodinet-0.1.2.dist-info/WHEEL
schrodinet-0.1.2.dist-info/top_level.txt
schrodinet-0.1.2.dist-info/RECORD
