Metadata-Version: 2.1
Name: schrodinet
Version: 0.1.2
Summary: Solving the Schrodinger equation using RBF Neural Net
Home-page: https://github.com/NLESC-JCER/Schrodinet
Author: ['Nicolas Renaud', 'Felipe Zapata']
Author-email: n.renaud@esciencecenter.nl
License: Apache Software License 2.0
Keywords: schrodinet
Classifier: Development Status :: 2 - Pre-Alpha
Classifier: Intended Audience :: Developers
Classifier: License :: OSI Approved :: Apache Software License
Classifier: Natural Language :: English
Classifier: Intended Audience :: Science/Research
Classifier: Programming Language :: Python :: 3.7
Classifier: Topic :: Scientific/Engineering :: Chemistry
License-File: LICENSE
License-File: NOTICE
Requires-Dist: autograd
Requires-Dist: cython
Requires-Dist: matplotlib
Requires-Dist: numpy
Requires-Dist: pyyaml (>=5.1)
Requires-Dist: schema
Requires-Dist: scipy
Requires-Dist: tqdm
Requires-Dist: torch
Provides-Extra: dev
Requires-Dist: prospector[with_pyroma] ; extra == 'dev'
Requires-Dist: yapf ; extra == 'dev'
Requires-Dist: isort ; extra == 'dev'
Provides-Extra: doc
Requires-Dist: recommonmark ; extra == 'doc'
Requires-Dist: sphinx ; extra == 'doc'
Requires-Dist: sphinx-rtd-theme ; extra == 'doc'
Provides-Extra: test
Requires-Dist: coverage ; extra == 'test'
Requires-Dist: pycodestyle ; extra == 'test'
Requires-Dist: pytest ; extra == 'test'
Requires-Dist: pytest-cov ; extra == 'test'
Requires-Dist: pytest-runner ; extra == 'test'
